LICENSE
MANIFEST.in
README.rst
setup.py
sphinxcontrib/__init__.py
sphinxcontrib/cmtinc.py
sphinxcontrib_cmtinc.egg-info/PKG-INFO
sphinxcontrib_cmtinc.egg-info/SOURCES.txt
sphinxcontrib_cmtinc.egg-info/dependency_links.txt
sphinxcontrib_cmtinc.egg-info/namespace_packages.txt
sphinxcontrib_cmtinc.egg-info/not-zip-safe
sphinxcontrib_cmtinc.egg-info/requires.txt
sphinxcontrib_cmtinc.egg-info/top_level.txt